{
  "unitName": "ou4",
  "side": "OPFOR",
  "units": [
    {
      "name": "ou4-c1",
      "identifier": "6VNCZ8WABD",
      "troopers": [
        {
          "identifier": "Q7CLDDU0WU",
          "name": "B1",
          "sl": 12
        },
        {
          "identifier": "27BO8TL93C",
          "name": "B1",
          "sl": 11
        },
        {
          "identifier": "8QRU7ZSFEN",
          "name": "B1",
          "sl": 11
        },
        {
          "identifier": "HMPWZER1CC",
          "name": "B1",
          "sl": 11
        },
        {
          "identifier": "STU958IGJY",
          "name": "B1",
          "sl": 11
        },
        {
          "identifier": "NAV7Z7H7DO",
          "name": "B1",
          "sl": 11
        },
        {
          "identifier": "JD4SFV8YQK",
          "name": "B1",
          "sl": 11
        },
        {
          "identifier": "9NSIKA94DD",
          "name": "B1",
          "sl": 11
        }
      ],
      "vehicles": []
    },
    {
      "name": "ou4-c2",
      "identifier": "OXU9LZCBK2",
      "troopers": [
        {
          "identifier": "RAAYUNNHMI",
          "name": "B1",
          "sl": 12
        },
        {
          "identifier": "XDRMEKKQP2",
          "name": "B1",
          "sl": 11
        },
        {
          "identifier": "HFLQ5J7OEF",
          "name": "B1",
          "sl": 11
        },
        {
          "identifier": "G7U0FCYYDL",
          "name": "B1",
          "sl": 11
        },
        {
          "identifier": "SHC0IF2WKR",
          "name": "B1",
          "sl": 11
        },
        {
          "identifier": "NFHIU1JFSY",
          "name": "B1",
          "sl": 11
        },
        {
          "identifier": "11WLFVLD4C",
          "name": "B1",
          "sl": 11
        },
        {
          "identifier": "9N6IVM1IM5",
          "name": "B1",
          "sl": 11
        }
      ],
      "vehicles": []
    },
    {
      "name": "ou4-c3",
      "identifier": "B8DMVE9545",
      "troopers": [
        {
          "identifier": "5JFSCH8WUR",
          "name": "B1",
          "sl": 12
        },
        {
          "identifier": "PZA06TVHBX",
          "name": "B1",
          "sl": 11
        },
        {
          "identifier": "4QH2DC27WF",
          "name": "B1",
          "sl": 11
        },
        {
          "identifier": "KSMP4L3T29",
          "name": "B1",
          "sl": 11
        },
        {
          "identifier": "MHLAQJCT6W",
          "name": "B1",
          "sl": 11
        },
        {
          "identifier": "KIOZDFRO7P",
          "name": "B1",
          "sl": 11
        },
        {
          "identifier": "IESLLJBD8U",
          "name": "B1",
          "sl": 11
        },
        {
          "identifier": "BFT9A48H20",
          "name": "B1",
          "sl": 11
        }
      ],
      "vehicles": []
    },
    {
      "name": "ou4-c4",
      "identifier": "3M61FH64FQ",
      "troopers": [
        {
          "identifier": "H7SF5DT4AM",
          "name": "B1",
          "sl": 12
        },
        {
          "identifier": "VJRT4C4X9F",
          "name": "B1",
          "sl": 11
        },
        {
          "identifier": "AYYE1W2G9T",
          "name": "B1",
          "sl": 11
        },
        {
          "identifier": "PFZ4IW4201",
          "name": "B1",
          "sl": 11
        },
        {
          "identifier": "RITKIITNSI",
          "name": "B1",
          "sl": 11
        },
        {
          "identifier": "SQKQID6L6F",
          "name": "B1",
          "sl": 11
        },
        {
          "identifier": "1IO5Y8CYZZ",
          "name": "B1",
          "sl": 11
        },
        {
          "identifier": "K4N4E4A9FW",
          "name": "B1",
          "sl": 11
        }
      ],
      "vehicles": []
    },
    {
      "name": "ou4-at",
      "identifier": "03NCXJYZQM",
      "troopers": [
        {
          "identifier": "70O70GB5C3",
          "name": "B1",
          "sl": 12
        },
        {
          "identifier": "HBZB7H4ANJ",
          "name": "B1",
          "sl": 11
        },
        {
          "identifier": "QG2AMWJXNM",
          "name": "B1",
          "sl": 11
        },
        {
          "identifier": "SHZ5EPRXWA",
          "name": "B1",
          "sl": 11
        },
        {
          "identifier": "KWHEOAZ5O1",
          "name": "B1",
          "sl": 11
        },
        {
          "identifier": "WA0QHU3NUB",
          "name": "B1",
          "sl": 11
        },
        {
          "identifier": "LGJHQJ8YPU",
          "name": "B1",
          "sl": 11
        },
        {
          "identifier": "XOAXI79X7L",
          "name": "B1",
          "sl": 11
        }
      ],
      "vehicles": []
    },
    {
      "name": "ou4-firesupport",
      "identifier": "MS5YF6YB5K",
      "troopers": [
        {
          "identifier": "NRN7J4PNAS",
          "name": "B1",
          "sl": 12
        },
        {
          "identifier": "E2VD7LBJ5R",
          "name": "B1",
          "sl": 11
        },
        {
          "identifier": "1SOAPZVR80",
          "name": "B1",
          "sl": 11
        },
        {
          "identifier": "66WCB3TETU",
          "name": "B1",
          "sl": 11
        },
        {
          "identifier": "RWBF296MD4",
          "name": "B1",
          "sl": 11
        },
        {
          "identifier": "QJ12GLW6OU",
          "name": "B1",
          "sl": 10
        },
        {
          "identifier": "IYFVY9ZO6O",
          "name": "B1",
          "sl": 11
        },
        {
          "identifier": "EII7GY3MGC",
          "name": "B1",
          "sl": 10
        }
      ],
      "vehicles": []
    },
    {
      "name": "ou4-marksman",
      "identifier": "ZLIWFAZPQK",
      "troopers": [
        {
          "identifier": "X9Q9ADVTHF",
          "name": "B1",
          "sl": 12
        },
        {
          "identifier": "V8JU7N9NT0",
          "name": "B1",
          "sl": 11
        },
        {
          "identifier": "2ONDTIRB9Q",
          "name": "B1",
          "sl": 11
        },
        {
          "identifier": "O9TA6S5NI5",
          "name": "B1",
          "sl": 11
        },
        {
          "identifier": "Y1V4B101FO",
          "name": "B1",
          "sl": 11
        },
        {
          "identifier": "OH9SCUGMBV",
          "name": "B1",
          "sl": 11
        },
        {
          "identifier": "RC559J0DUH",
          "name": "B1",
          "sl": 11
        },
        {
          "identifier": "QIGQKEKCI5",
          "name": "B1",
          "sl": 11
        }
      ],
      "vehicles": []
    }
  ]
}